linearAlgebraCalc/__init__.py
linearAlgebraCalc/basicOperations.py
linearAlgebraCalc/eigan.py
linearAlgebraCalc/equations.py
linearAlgebraCalc/globalFunctions.py
linearAlgebraCalc/matrixOperations.py
linearAlgebraCalc/main/__init__.py
linearAlgebraCalc-0.0.21.dist-info/METADATA
linearAlgebraCalc-0.0.21.dist-info/WHEEL
linearAlgebraCalc-0.0.21.dist-info/top_level.txt
linearAlgebraCalc-0.0.21.dist-info/RECORD
