Metadata-Version: 2.1
Name: linearAlgebraCalc
Version: 0.0.21
Summary: Linear Algebra Calculator with simple functions
Author: Aditya Srikanth
Author-email: aditya.srikanth11@gmail.com
License: UNKNOWN
Keywords: python,mathamatics,Linear Algebra,Vectors,Eigen Values
Platform: UNKNOWN
Classifier: Development Status :: 1 - Planning
Classifier: Intended Audience :: Developers
Classifier: Programming Language :: Python :: 3
Classifier: Operating System :: Unix
Classifier: Operating System :: MacOS :: MacOS X
Classifier: Operating System :: Microsoft :: Windows
